Metadata-Version: 2.4
Name: scriptthing
Version: 0.2.1
Summary: A tool for managing scripts in various languages with powerful output formatting capabilities
Requires-Python: >=3.10
Requires-Dist: click
Requires-Dist: jinja2
Requires-Dist: pyyaml
Requires-Dist: toml
Requires-Dist: humanfriendly>=10.0
Requires-Dist: pydantic>=2.0.0
Provides-Extra: test
Requires-Dist: pytest>=7.0.0; extra == "test"
Provides-Extra: mcp
Requires-Dist: fastmcp; extra == "mcp"
Requires-Dist: shellmcp; extra == "mcp"
Dynamic: provides-extra
Dynamic: requires-dist
Dynamic: requires-python
